{
  "debugger": "debugger",
  "hotfix": "热更新框架",
  "resource": "resource",
  "shader": "shader",
  "vr": "vr",
  "addressable": "Addressable",
  "animation": "动画",
  "assetBundle": "AssetBundle",
  "camera": "相机",
  "dotween": "DOTween",
  "editorGUI": "EditorGUI",
  "esc": "ESC",
  "frame": "帧率优化",
  "GameObject": "GameObject",
  "hack": "游戏加密和破解",
  "line": "流水线",
  "memory": "内存优化",
  "mobile": "手游平台优化",
  "pathfinding": "寻路算法",
  "picture": "图片压缩",
  "pool": "对象池框架",
  "ray": "射线",
  "transform": "Transform",
  "ugui": "UGUI",
  "unity": "Unity"
}